{"cameraMode":{"drawMode":0,"name":"Shaded","section":"Shading Mode"},"sceneLighting":true,"audioPlay":false,"sceneViewState":{"m_AlwaysRefresh":false,"showFog":true,"showSkybox":true,"showFlares":true,"showImageEffects":true,"showParticleSystems":true,"showVisualEffectGraphs":true,"m_FxEnabled":true},"in2DMode":false,"pivot":{"x":12.34041976928711,"y":-17.28960418701172,"z":14.099105834960938},"rotation":{"x":-0.33557137846946719,"y":-0.30766773223876955,"z":0.11697610467672348,"w":-0.8826545476913452},"size":20.322893142700197,"orthographic":false}